loadconfig/__init__.py
loadconfig/lib.py
loadconfig-0.2.1.data/scripts/loadconfig
loadconfig-0.2.1.dist-info/METADATA
loadconfig-0.2.1.dist-info/WHEEL
loadconfig-0.2.1.dist-info/top_level.txt
loadconfig-0.2.1.dist-info/RECORD
