Metadata-Version: 2.4
Name: loadconfig
Version: 0.2.1
Summary: Tool to simplify config management in a program
Author-email: Daniel Mizyrycki <mzdaniel@glidelink.net>
License: The MIT License (MIT)
Project-URL: Homepage, https://loadconfig.readthedocs.org
Project-URL: Repository, https://github.com/loadconfig
Keywords: config,yaml,clg,command-line,argparse
Classifier: License :: OSI Approved :: MIT License
Classifier: Development Status :: 4 - Beta
Classifier: Intended Audience :: Developers
Classifier: Intended Audience :: System Administrators
Classifier: Programming Language :: Python
Classifier: Programming Language :: Python :: 3
Classifier: Programming Language :: Python :: 3.11
Classifier: Programming Language :: Python :: 3.12
Classifier: Programming Language :: Python :: 3.13
Classifier: Programming Language :: Python :: 3.14
Classifier: Topic :: Utilities
Classifier: Topic :: Software Development :: Libraries :: Python Modules
Classifier: Operating System :: POSIX
Classifier: Operating System :: Unix
Requires-Python: >=3.11
Requires-Dist: clg>=3.3
Requires-Dist: PyYAML>=6.0.2
